{
  "type": "fruitstack:cooking",
  "ingredients": [
    {
      "item": "fruitstack:glutinous_rice"
    },
    {
      "item": "fruitstack:glutinous_rice"
    },
    {
      "item": "fruitstack:glutinous_rice"
    },
    {
      "item": "fruitstack:glutinous_rice"
    },
    {
      "item": "fruitstack:jujube_filling"
    },
    {
      "item": "fruitstack:jujube_filling"
    },
    {
      "item": "fruitstack:jujube_filling"
    },
    {
      "item": "fruitstack:jujube_filling"
    }
  ],
  "result": {
    "item": "fruitstack:jujube_rice_dumpling_block"
  },
  "container": {
    "item": "fruitstack:rice_dumpling_pot"
  },
  "experience": 1.0,
  "cookingtime": 200
}